pepperbot_ai_query/__init__.py
pepperbot_ai_query/config.py
pepperbot_ai_query/main.py
pepperbot_ai_query/manage.py
pepperbot_ai_query/orm.py
pepperbot_ai_query/utils.py
pepperbot_ai_query/models/gpt/main.py
pepperbot_ai_query-0.0.2.dist-info/METADATA
pepperbot_ai_query-0.0.2.dist-info/WHEEL
pepperbot_ai_query-0.0.2.dist-info/top_level.txt
pepperbot_ai_query-0.0.2.dist-info/RECORD
